README.rst
setup.cfg
setup.py
src/packerlicious/__init__.py
src/packerlicious/builder.py
src/packerlicious/post_processor.py
src/packerlicious/provisioner.py
src/packerlicious/template.py
src/packerlicious/validator.py
src/packerlicious/version.py
src/packerlicious.egg-info/PKG-INFO
src/packerlicious.egg-info/SOURCES.txt
src/packerlicious.egg-info/dependency_links.txt
src/packerlicious.egg-info/requires.txt
src/packerlicious.egg-info/top_level.txt
src/packerlicious/community/__init__.py
src/packerlicious/community/builder.py
src/packerlicious/community/post_processor.py
src/packerlicious/community/provisioner.py
src/thirdparty/__init__.py
src/thirdparty/troposphere/__init__.py