Metadata-Version: 1.1
Name: packerlicious
Version: 1.4.2
Summary: packerlicious - a python wrapper for hashicorp packer templates.
Home-page: https://github.com/mayn/packerlicious
Author: Matthew Aynalem
Author-email: maynalem@gmail.com
License: Apache License 2.0
Keywords: hashicorp packer
Platform: UNKNOWN
Classifier: License :: OSI Approved :: Apache Software License
Classifier: Programming Language :: Python :: 2
Classifier: Programming Language :: Python :: 2.7
Classifier: Programming Language :: Python :: 3
Classifier: Programming Language :: Python :: 3.4
Classifier: Programming Language :: Python :: 3.5
Classifier: Programming Language :: Python :: 3.6
Classifier: Programming Language :: Python :: 3.7
